{
  "schema": 1,
  "meta": {
    "date_utc": "2026-07-15T03:55:29+00:00",
    "stamp": "20260715T035529Z",
    "git_sha": "6d967d1",
    "git_dirty": false,
    "machine": {
      "cpu": "Intel(R) Core(TM) i7-10700F CPU @ 2.90GHz",
      "nproc": 16,
      "os": "Linux 6.14.0-37-generic"
    },
    "tier": "quick",
    "axes": [
      "speed",
      "parity",
      "quality",
      "fuzz",
      "goldens"
    ],
    "width": 256,
    "height": 256,
    "quality_width": 96,
    "quality_height": 96,
    "runs": 1,
    "f3_bin": "/home/gistarcade/src/fractall-rust/fraktaler-3-3.1/fraktaler-3-3.1.linux",
    "mem_limit_mb": 34024,
    "quarantined": [
      "e52465"
    ],
    "fuzz_seed": 20260714
  },
  "speed": {
    "status": "ok",
    "cases": {
      "test5": {
        "fractall_s": 0.0111,
        "f3_s": 0.0175,
        "ratio": 0.6343,
        "status": "ok",
        "f3_exr_ok": true
      },
      "spiral": {
        "fractall_s": 0.0362,
        "f3_s": 0.166,
        "ratio": 0.2181,
        "status": "ok",
        "f3_exr_ok": true
      },
      "flake": {
        "fractall_s": 0.0689,
        "f3_s": 0.2177,
        "ratio": 0.3165,
        "status": "ok",
        "f3_exr_ok": true
      },
      "glitch_test_2": {
        "fractall_s": 0.0684,
        "f3_s": 0.1659,
        "ratio": 0.4123,
        "status": "ok",
        "f3_exr_ok": true
      },
      "e50": {
        "fractall_s": 0.1667,
        "f3_s": 1.1678,
        "ratio": 0.1427,
        "status": "ok",
        "f3_exr_ok": true
      },
      "e113": {
        "fractall_s": 0.066,
        "f3_s": 0.2662,
        "ratio": 0.2479,
        "status": "ok",
        "f3_exr_ok": true
      },
      "e401": {
        "fractall_s": 0.5208,
        "f3_s": 6.3773,
        "ratio": 0.0817,
        "status": "ok",
        "f3_exr_ok": true
      },
      "e1000": {
        "fractall_s": 0.4185,
        "f3_s": 2.971,
        "ratio": 0.1409,
        "status": "ok",
        "f3_exr_ok": true
      },
      "floral_fantasy": {
        "fractall_s": 0.0372,
        "f3_s": 0.1661,
        "ratio": 0.224,
        "status": "ok",
        "f3_exr_ok": true
      },
      "dragon": {
        "fractall_s": 1.67,
        "f3_s": 3.6226,
        "ratio": 0.461,
        "status": "ok",
        "f3_exr_ok": true
      }
    },
    "geomean_ratio": 0.2444,
    "worst_ratio": {
      "case": "test5",
      "ratio": 0.6343
    },
    "wins": [
      "test5",
      "spiral",
      "flake",
      "glitch_test_2",
      "e50",
      "e113",
      "e401",
      "e1000",
      "floral_fantasy",
      "dragon"
    ],
    "timeouts": [],
    "excluded_f3_degenerate": [],
    "n_cases": 10,
    "n_compared": 10
  },
  "parity": {
    "status": "ok",
    "cases": {
      "dragon": {
        "status": "ok",
        "rel_dsi_pct": 0.1714,
        "mean_abs_dsi": 8568.8423,
        "inside_mismatch": 28,
        "f3_degenerate": false,
        "f3_secs_num": 3.5811,
        "fr_secs_num": 1.6469
      },
      "e1000": {
        "status": "ok",
        "rel_dsi_pct": 0.001,
        "mean_abs_dsi": 0.3236,
        "inside_mismatch": 0,
        "f3_degenerate": false,
        "f3_secs_num": 2.9744,
        "fr_secs_num": 0.4279
      },
      "e113": {
        "status": "ok",
        "rel_dsi_pct": 0.0786,
        "mean_abs_dsi": 27.8825,
        "inside_mismatch": 0,
        "f3_degenerate": false,
        "f3_secs_num": 0.2335,
        "fr_secs_num": 0.051
      },
      "e401": {
        "status": "ok",
        "rel_dsi_pct": 0.004,
        "mean_abs_dsi": 8.5156,
        "inside_mismatch": 0,
        "f3_degenerate": false,
        "f3_secs_num": 6.3203,
        "fr_secs_num": 0.5138
      },
      "e50": {
        "status": "ok",
        "rel_dsi_pct": 0.0347,
        "mean_abs_dsi": 91.2391,
        "inside_mismatch": 0,
        "f3_degenerate": false,
        "f3_secs_num": 1.1202,
        "fr_secs_num": 0.1632
      },
      "flake": {
        "status": "ok",
        "rel_dsi_pct": 0.0434,
        "mean_abs_dsi": 26.0319,
        "inside_mismatch": 0,
        "f3_degenerate": false,
        "f3_secs_num": 0.1699,
        "fr_secs_num": 0.0619
      },
      "floral_fantasy": {
        "status": "ok",
        "rel_dsi_pct": 0.0032,
        "mean_abs_dsi": 0.3894,
        "inside_mismatch": 0,
        "f3_degenerate": false,
        "f3_secs_num": 0.1402,
        "fr_secs_num": 0.0301
      },
      "glitch_test_2": {
        "status": "ok",
        "rel_dsi_pct": 0.0079,
        "mean_abs_dsi": 19.7256,
        "inside_mismatch": 12,
        "f3_degenerate": false,
        "f3_secs_num": 0.1135,
        "fr_secs_num": 0.0424
      },
      "spiral": {
        "status": "ok",
        "rel_dsi_pct": 0.979,
        "mean_abs_dsi": 9.7899,
        "inside_mismatch": 16,
        "f3_degenerate": false,
        "f3_secs_num": 0.1672,
        "fr_secs_num": 0.0248
      },
      "test5": {
        "status": "ok",
        "rel_dsi_pct": 0.0,
        "mean_abs_dsi": 0.0,
        "inside_mismatch": 0,
        "f3_degenerate": false,
        "f3_secs_num": 0.0162,
        "fr_secs_num": 0.0102
      }
    },
    "n_ok": 10,
    "n_pixel_equiv": 5,
    "n_fail": 0,
    "n_timeout": 0,
    "n_f3_degenerate": 0
  },
  "quality": {
    "status": "ok",
    "n_pass": 15,
    "n_warn": 0,
    "n_fail": 0,
    "fail_presets": [],
    "warn_presets": [],
    "presets": [
      {
        "name": "seahorse-valley",
        "verdict": "PASS",
        "max_iter_diff": null,
        "p99_iter_diff": null,
        "divergence_ratio": 0.0,
        "time_pert_ms": 265.372145,
        "time_gmp_ms": 1028.7345500000001
      },
      {
        "name": "mandelbrot-e13",
        "verdict": "PASS",
        "max_iter_diff": null,
        "p99_iter_diff": null,
        "divergence_ratio": 0.0,
        "time_pert_ms": 24.98183,
        "time_gmp_ms": 337.948239
      },
      {
        "name": "mandelbrot-e17",
        "verdict": "PASS",
        "max_iter_diff": null,
        "p99_iter_diff": null,
        "divergence_ratio": 0.0,
        "time_pert_ms": 4.176081,
        "time_gmp_ms": 426.110143
      },
      {
        "name": "misiurewicz-m32",
        "verdict": "PASS",
        "max_iter_diff": null,
        "p99_iter_diff": null,
        "divergence_ratio": 0.0,
        "time_pert_ms": 92.135757,
        "time_gmp_ms": 371.824706
      },
      {
        "name": "julia-siegel-disk",
        "verdict": "PASS",
        "max_iter_diff": null,
        "p99_iter_diff": null,
        "divergence_ratio": 0.0,
        "time_pert_ms": 1.057933,
        "time_gmp_ms": 209.896415
      },
      {
        "name": "burning-ship-antenna",
        "verdict": "PASS",
        "max_iter_diff": null,
        "p99_iter_diff": null,
        "divergence_ratio": 0.0,
        "time_pert_ms": 1.237269,
        "time_gmp_ms": 27.069524
      },
      {
        "name": "tricorn-spiral",
        "verdict": "PASS",
        "max_iter_diff": null,
        "p99_iter_diff": null,
        "divergence_ratio": 0.0,
        "time_pert_ms": 0.799498,
        "time_gmp_ms": 9.848719000000001
      },
      {
        "name": "celtic-fold-edge",
        "verdict": "PASS",
        "max_iter_diff": null,
        "p99_iter_diff": null,
        "divergence_ratio": 0.0,
        "time_pert_ms": 21.067761,
        "time_gmp_ms": 3430.888317
      },
      {
        "name": "buffalo-fold-edge",
        "verdict": "PASS",
        "max_iter_diff": null,
        "p99_iter_diff": null,
        "divergence_ratio": 0.0,
        "time_pert_ms": 25.36998,
        "time_gmp_ms": 3859.231769
      },
      {
        "name": "perpbs-escape-band",
        "verdict": "PASS",
        "max_iter_diff": null,
        "p99_iter_diff": null,
        "divergence_ratio": 0.0,
        "time_pert_ms": 18.707736999999998,
        "time_gmp_ms": 2674.940198
      },
      {
        "name": "mandelbrot-e18-minibrot",
        "verdict": "PASS",
        "max_iter_diff": null,
        "p99_iter_diff": null,
        "divergence_ratio": 0.0,
        "time_pert_ms": 89.30893400000001,
        "time_gmp_ms": 384.246525
      },
      {
        "name": "mandelbrot-e30",
        "verdict": "PASS",
        "max_iter_diff": null,
        "p99_iter_diff": null,
        "divergence_ratio": 0.0,
        "time_pert_ms": 4915.653211000001,
        "time_gmp_ms": 21323.149026
      },
      {
        "name": "mandelbrot-e50",
        "verdict": "PASS",
        "max_iter_diff": null,
        "p99_iter_diff": null,
        "divergence_ratio": 0.0,
        "time_pert_ms": 7950.009255,
        "time_gmp_ms": 180563.384769
      },
      {
        "name": "mandelbrot-e100",
        "verdict": "PASS",
        "max_iter_diff": null,
        "p99_iter_diff": null,
        "divergence_ratio": 0.0,
        "time_pert_ms": 514.352837,
        "time_gmp_ms": 20593.784608
      },
      {
        "name": "single-ref-glitch-interior",
        "verdict": "PASS",
        "max_iter_diff": null,
        "p99_iter_diff": null,
        "divergence_ratio": 0.0,
        "time_pert_ms": 37.668497,
        "time_gmp_ms": 1849.7697400000002
      }
    ]
  },
  "fuzz": {
    "status": "ok",
    "seed": 20260714,
    "n_probes": 3,
    "n_pass": 3,
    "n_warn": 0,
    "n_fail": 0,
    "cases": {
      "fuzz-20260714-0-tricorn": {
        "verdict": "PASS",
        "type": "tricorn",
        "center_x": "-0.5912971496582031",
        "center_y": "-0.043022791544596366",
        "zoom": "9.005324e+05",
        "iterations": 2048
      },
      "fuzz-20260714-1-mandelbrot": {
        "verdict": "PASS",
        "type": "mandelbrot",
        "center_x": "-0.6152286330858866",
        "center_y": "0.40106525023778294",
        "zoom": "6.023813e+07",
        "iterations": 2048
      },
      "fuzz-20260714-2-tricorn": {
        "verdict": "PASS",
        "type": "tricorn",
        "center_x": "0.25293623520216574",
        "center_y": "-0.10817046263643233",
        "zoom": "9.216840e+09",
        "iterations": 2048
      }
    },
    "fail_cases": [],
    "warn_cases": []
  },
  "goldens": {
    "passed": true,
    "detail": ""
  },
  "beyond_f3": {
    "speed_wins": [
      "test5",
      "spiral",
      "flake",
      "glitch_test_2",
      "e50",
      "e113",
      "e401",
      "e1000",
      "floral_fantasy",
      "dragon"
    ],
    "correctness_wins": []
  },
  "gaps": []
}